Games/Air_Hockey.py
Games/Dodge_Ball.py
Games/Tic_Tac_Toe.py
Games/__init__.py
Games_Rishit-1.0.0.dist-info/LICENSE
Games_Rishit-1.0.0.dist-info/METADATA
Games_Rishit-1.0.0.dist-info/WHEEL
Games_Rishit-1.0.0.dist-info/top_level.txt
Games_Rishit-1.0.0.dist-info/RECORD
