Metadata-Version: 2.1
Name: Games_Rishit
Version: 1.0.0
Summary: A collection of mini-games: Tic-Tac-Toe, Air Hockey, and Dodgeball.
Author: Rishit Dhiman
Author-email: dhimanrishit21@gmail.com
Classifier: Development Status :: 5 - Production/Stable
Classifier: License :: OSI Approved :: MIT License
Classifier: Programming Language :: Python :: 3
Classifier: Operating System :: OS Independent
Requires-Python: >=3.6
License-File: LICENSE
Requires-Dist: pygame
Requires-Dist: numpy
